OpenFisca_France_Pension-0.1.2.data/data/share/openfisca/openfisca-france-pension/CHANGELOG.md
OpenFisca_France_Pension-0.1.2.data/data/share/openfisca/openfisca-france-pension/LICENSE
OpenFisca_France_Pension-0.1.2.data/data/share/openfisca/openfisca-france-pension/README.md
openfisca_france_pension/__init__.py
openfisca_france_pension/entities.py
openfisca_france_pension/tools.py
openfisca_france_pension/units.yaml
openfisca_france_pension/parameters/marche_travail/index.yaml
openfisca_france_pension/parameters/marche_travail/indemnite_fin_contrat/index.yaml
openfisca_france_pension/parameters/marche_travail/indemnite_fin_contrat/taux.yaml
openfisca_france_pension/parameters/marche_travail/primes_exceptionnelles/index.yaml
openfisca_france_pension/parameters/marche_travail/primes_exceptionnelles/prime_partage_valeur/index.yaml
openfisca_france_pension/parameters/marche_travail/primes_exceptionnelles/prime_partage_valeur/plafond_exoneration.yaml
openfisca_france_pension/parameters/marche_travail/primes_exceptionnelles/prime_partage_valeur/plafond_exoneration_avec_accord_interessement.yaml
openfisca_france_pension/parameters/marche_travail/primes_exceptionnelles/prime_partage_valeur/plafond_salaire.yaml
openfisca_france_pension/parameters/marche_travail/primes_exceptionnelles/prime_pepa/index.yaml
openfisca_france_pension/parameters/marche_travail/primes_exceptionnelles/prime_pepa/plafond_effectif_entreprise.yaml
openfisca_france_pension/parameters/marche_travail/primes_exceptionnelles/prime_pepa/plafond_exoneration.yaml
openfisca_france_pension/parameters/marche_travail/primes_exceptionnelles/prime_pepa/plafond_exoneration_avec_accord_interessement.yaml
openfisca_france_pension/parameters/marche_travail/primes_exceptionnelles/prime_pepa/plafond_salaire.yaml
openfisca_france_pension/parameters/marche_travail/remuneration_dans_fonction_publique/index.yaml
OpenFisca_France_Pension-0.1.2.dist-info/LICENSE
OpenFisca_France_Pension-0.1.2.dist-info/METADATA
OpenFisca_France_Pension-0.1.2.dist-info/WHEEL
OpenFisca_France_Pension-0.1.2.dist-info/top_level.txt
OpenFisca_France_Pension-0.1.2.dist-info/RECORD
