Metadata-Version: 2.1
Name: OpenFisca-France-Pension
Version: 0.1.2
Summary: OpenFisca tax and benefit system for France-Pension
Home-page: https://github.com/openfisca/openfisca-france-pension
Author: OpenFisca Team
Author-email: contact@openfisca.org
License: http://www.fsf.org/licensing/licenses/agpl-3.0.html
Keywords: benefit microsimulation social tax
Platform: UNKNOWN
Classifier: Development Status :: 5 - Production/Stable
Classifier: License :: OSI Approved :: GNU Affero General Public License v3
Classifier: Operating System :: POSIX
Classifier: Programming Language :: Python
Classifier: Topic :: Scientific/Engineering :: Information Analysis
Requires-Python: >=3.9
License-File: LICENSE
Requires-Dist: bottleneck<=2.0.0,>=1.3.2
Requires-Dist: OpenFisca-Core<44,>=41.5.0
Requires-Dist: numba<1.0.0,>=0.54
Requires-Dist: pandas<3.0,>=2.0
Provides-Extra: dev
Requires-Dist: autopep8; extra == "dev"
Requires-Dist: flake8<4.0,>=3.9; extra == "dev"
Requires-Dist: flake8-import-order; extra == "dev"
Requires-Dist: flake8-print; extra == "dev"
Requires-Dist: pycodestyle>=2.6.0; extra == "dev"
